VeryPy/VeryPy.py
VeryPy/__init__.py
VeryPy-1.0.5.dist-info/LICENSE.txt
VeryPy-1.0.5.dist-info/METADATA
VeryPy-1.0.5.dist-info/WHEEL
VeryPy-1.0.5.dist-info/top_level.txt
VeryPy-1.0.5.dist-info/RECORD
