Metadata-Version: 2.1
Name: VeryPy
Version: 1.0.5
Summary: An inline run-time file integrity checker
Home-page: UNKNOWN
Author: Sombodee (Landon Hutchins) - Travis Mackey - Joe Alagoa 
License: MIT
Keywords: run-time,Fernet,SHA-1,Integrity
Platform: UNKNOWN
Classifier: Development Status :: 5 - Production/Stable
Classifier: Topic :: Software Development :: Build Tools
Classifier: Programming Language :: Python :: 3
